dispike/__init__.py
dispike/creating/__init__.py
dispike/creating/allowed_mentions.py
dispike/creating/components.py
dispike/creating/models/__init__.py
dispike/creating/models/options.py
dispike/creating/models/permissions.py
dispike/creating/registrator.py
dispike/errors/__init__.py
dispike/errors/components.py
dispike/errors/dispike.py
dispike/errors/events.py
dispike/errors/network.py
dispike/errors/response.py
dispike/errors/warnings.py
dispike/eventer.py
dispike/eventer_helpers/__init__.py
dispike/eventer_helpers/determine_event_information.py
dispike/followup/__init__.py
dispike/followup/main.py
dispike/followup/storage/__init__.py
dispike/helper/__init__.py
dispike/helper/acknowledgements.md
dispike/helper/color.py
dispike/helper/embed.py
dispike/helper/embed_types.py
dispike/helper/network_request_log.py
dispike/helper/permissions_generator.py
dispike/helper/utils.py
dispike/incoming/__init__.py
dispike/incoming/attribute_helpers/__init__.py
dispike/incoming/attribute_helpers/resolved_interactions.py
dispike/incoming/discord_types/__init__.py
dispike/incoming/discord_types/channel.py
dispike/incoming/discord_types/member.py
dispike/incoming/discord_types/message.py
dispike/incoming/discord_types/role.py
dispike/incoming/discord_types/user.py
dispike/incoming/incoming_interactions.py
dispike/interactions.py
dispike/main.py
dispike/middlewares/__init__.py
dispike/middlewares/verification.py
dispike/response.py
dispike/server.py
dispike-1.0.1b0.dist-info/LICENSE
dispike-1.0.1b0.dist-info/WHEEL
dispike-1.0.1b0.dist-info/METADATA
dispike-1.0.1b0.dist-info/RECORD
