Metadata-Version: 2.1
Name: dispike
Version: 1.0.1b0
Summary: An independent, simple to use, powerful framework for creating interaction-based Discord bots. Powered by FastAPI
Home-page: https://github.com/ms7m/dispike
License: MIT
Author: Mustafa Mohamed
Author-email: ms7mohamed@gmail.com
Requires-Python: >=3.6.1,<4.0
Classifier: License :: OSI Approved :: MIT License
Classifier: Programming Language :: Python :: 3
Classifier: Programming Language :: Python :: 3.7
Classifier: Programming Language :: Python :: 3.8
Classifier: Programming Language :: Python :: 3.9
Requires-Dist: PyNaCl (>=1.4.0,<2.0.0)
Requires-Dist: async-timeout (>=3.0.1,<4.0.0)
Requires-Dist: fastapi (>=0.63.0,<0.64.0)
Requires-Dist: httpx (>=0.16.1,<0.17.0)
Requires-Dist: loguru (>=0.5.3,<0.6.0)
Requires-Dist: pydantic (==1.8.2)
Requires-Dist: typing-extensions (>=3.7.4,<4.0.0)
Requires-Dist: uvicorn (>=0.13.2,<0.14.0)
Project-URL: Documentation, https://dispike.ms7m.me?ref=pypi
Project-URL: Repository, https://github.com/ms7m/dispike
